graph2vec
