Metadata-Version: 1.1
Name: graph2vec
Version: 0.0.2
Summary: meaningful vector representations of nodes
Home-page: https://github.com/allentran/graph2vec
Author: Allen Tran
Author-email: realallentran@gmail.com
License: UNKNOWN
Platform: UNKNOWN
Classifier: Development Status :: 4 - Beta
Classifier: Programming Language :: Python
Classifier: Operating System :: Unix
Classifier: Operating System :: MacOS
